<?xml version="1.0" encoding="utf-8" ?>
<dwsync>
<file name="page6.html" server="capnum-doc.intranet.dgfip//part/" local="131408069850028776" remote="131412147000000000" Dst="2" />
<file name="page7.html" server="capnum-doc.intranet.dgfip//part/" local="131408069850078776" remote="131412147000000000" Dst="2" />
<file name="page8.html" server="capnum-doc.intranet.dgfip//part/" local="131408069850103776" remote="131412147000000000" Dst="2" />
<file name="page9.html" server="capnum-doc.intranet.dgfip//part/" local="131408069850128776" remote="131412147000000000" Dst="2" />
<file name="page10.html" server="capnum-doc.intranet.dgfip//part/" local="131408069849678776" remote="131412147000000000" Dst="2" />
<file name="page11.html" server="capnum-doc.intranet.dgfip//part/" local="131408069849703776" remote="131412147000000000" Dst="2" />
<file name="page12.html" server="capnum-doc.intranet.dgfip//part/" local="131408069849728776" remote="131412147000000000" Dst="2" />
<file name="page13.html" server="capnum-doc.intranet.dgfip//part/" local="131408069849753776" remote="131412147000000000" Dst="2" />
<file name="page14.html" server="capnum-doc.intranet.dgfip//part/" local="131408069849778776" remote="131412147000000000" Dst="2" />
<file name="page15.html" server="capnum-doc.intranet.dgfip//part/" local="131408069850003776" remote="131412147000000000" Dst="2" />
<file name="page16.html" server="capnum-doc.intranet.dgfip//part/" local="131408069857178776" remote="131412147000000000" Dst="2" />
</dwsync>