<?xml version="1.0" encoding="utf-8" ?>
<dwsync>
<file name="page1.JPG" server="capnum-doc.intranet.dgfip//part/" local="131432865622088970" remote="131679220800000000" Dst="2" />
<file name="page12.JPG" server="capnum-doc.intranet.dgfip//part/" local="131431285416191270" remote="131679220800000000" Dst="2" />
<file name="page11.JPG" server="capnum-doc.intranet.dgfip//part/" local="131431285219106200" remote="131679220800000000" Dst="2" />
<file name="page10.JPG" server="capnum-doc.intranet.dgfip//part/" local="131431275560667790" remote="131679220800000000" Dst="2" />
<file name="page13.JPG" server="capnum-doc.intranet.dgfip//part/" local="131431285624275520" remote="131679220800000000" Dst="2" />
<file name="page14.JPG" server="capnum-doc.intranet.dgfip//part/" local="131431286741830870" remote="131679220800000000" Dst="2" />
<file name="page1bis.JPG" server="capnum-doc.intranet.dgfip//part/" local="131432865824203620" remote="131679220800000000" Dst="2" />
<file name="page15.JPG" server="capnum-doc.intranet.dgfip//part/" local="131431287138940790" remote="131679220800000000" Dst="2" />
<file name="page2.JPG" server="capnum-doc.intranet.dgfip//part/" local="131431265376729130" remote="131679220800000000" Dst="2" />
<file name="page3.JPG" server="capnum-doc.intranet.dgfip//part/" local="131431265595242530" remote="131679220800000000" Dst="2" />
<file name="page5.JPG" server="capnum-doc.intranet.dgfip//part/" local="131431268078344480" remote="131679220800000000" Dst="2" />
<file name="page4.JPG" server="capnum-doc.intranet.dgfip//part/" local="131431267422514170" remote="131679220800000000" Dst="2" />
<file name="page5bis.JPG" server="capnum-doc.intranet.dgfip//part/" local="131431268587035940" remote="131679220800000000" Dst="2" />
<file name="page7.JPG" server="capnum-doc.intranet.dgfip//part/" local="131431274142585180" remote="131679220800000000" Dst="2" />
<file name="page6.JPG" server="capnum-doc.intranet.dgfip//part/" local="131431273942540330" remote="131679220800000000" Dst="2" />
<file name="page8.JPG" server="capnum-doc.intranet.dgfip//part/" local="131431274968912580" remote="131679220800000000" Dst="2" />
<file name="page9.JPG" server="capnum-doc.intranet.dgfip//part/" local="131431288119976550" remote="131679220800000000" Dst="2" />
</dwsync>