<?xml version="1.0" encoding="utf-8" ?>
<dwsync>
<file name="accuse_brouillons.gif" server="capnum-doc.intranet.dgfip//part/" local="131116603105818990" remote="131412148200000000" Dst="2" />
<file name="ajoutdoc.gif" server="capnum-doc.intranet.dgfip//part/" local="131116603106499020" remote="131412148200000000" Dst="2" />
<file name="ajoutdocante.gif" server="capnum-doc.intranet.dgfip//part/" local="131116603099779270" remote="131412148200000000" Dst="2" />
<file name="ajoutdocfin.gif" server="capnum-doc.intranet.dgfip//part/" local="131116603099129310" remote="131412148200000000" Dst="2" />
<file name="brouillons1bis.gif" server="capnum-doc.intranet.dgfip//part/" local="131116603092769600" remote="131412148200000000" Dst="2" />
<file name="brouillons2.gif" server="capnum-doc.intranet.dgfip//part/" local="131116603086489890" remote="131412148200000000" Dst="2" />
<file name="brouillons3.gif" server="capnum-doc.intranet.dgfip//part/" local="131116603086049910" remote="131412148200000000" Dst="2" />
<file name="brouillons3info1.gif" server="capnum-doc.intranet.dgfip//part/" local="131116603080140190" remote="131412148200000000" Dst="2" />
<file name="brouillons4.gif" server="capnum-doc.intranet.dgfip//part/" local="131116603079750220" remote="131412148200000000" Dst="2" />
<file name="brouillons5.gif" server="capnum-doc.intranet.dgfip//part/" local="131116603073880520" remote="131412148200000000" Dst="2" />
<file name="brouillons6.gif" server="capnum-doc.intranet.dgfip//part/" local="131116603073550490" remote="131412148200000000" Dst="2" />
<file name="brouillons8.gif" server="capnum-doc.intranet.dgfip//part/" local="131116603067050790" remote="131412148200000000" Dst="2" />
<file name="brouillons7.gif" server="capnum-doc.intranet.dgfip//part/" local="131116603067710770" remote="131412148200000000" Dst="2" />
<file name="brouillonsend.gif" server="capnum-doc.intranet.dgfip//part/" local="131116603060551100" remote="131412148200000000" Dst="2" />
<file name="brouillon_vide.gif" server="capnum-doc.intranet.dgfip//part/" local="131116603092329620" remote="131412148200000000" Dst="2" />
<file name="brouillons_acces.gif" server="capnum-doc.intranet.dgfip//part/" local="131116603061191070" remote="131412148200000000" Dst="2" />
<file name="brouilons1.gif" server="capnum-doc.intranet.dgfip//part/" local="131116603054651370" remote="131412148200000000" Dst="2" />
<file name="confirm_suppresion_pj.gif" server="capnum-doc.intranet.dgfip//part/" local="131116603054321420" remote="131412148200000000" Dst="2" />
<file name="entete.gif" server="capnum-doc.intranet.dgfip//part/" local="131116603049631590" remote="131412148200000000" Dst="2" />
<file name="survol_developpeadresse.gif" server="capnum-doc.intranet.dgfip//part/" local="131116603044891830" remote="131412148200000000" Dst="2" />
<file name="message abandon.gif" server="capnum-doc.intranet.dgfip//part/" local="131116603047721700" remote="131412148200000000" Dst="2" />
</dwsync>