<?xml version="1.0" encoding="utf-8" ?>
<dwsync>
<file name="mdp.html" server="capnum-doc.intranet.dgfip//part/" local="131691405099577214" remote="131691415200000000" Dst="2" />
<file name="page1.html" server="capnum-doc.intranet.dgfip//part/" local="131691405100114714" remote="131691415200000000" Dst="2" />
<file name="page2.html" server="capnum-doc.intranet.dgfip//part/" local="131691405100402214" remote="131691415200000000" Dst="2" />
<file name="page3.html" server="capnum-doc.intranet.dgfip//part/" local="131691405100739714" remote="131691415200000000" Dst="2" />
<file name="page4.html" server="capnum-doc.intranet.dgfip//part/" local="131691405101202214" remote="131691415200000000" Dst="2" />
<file name="page4a.html" server="capnum-doc.intranet.dgfip//part/" local="131691405101514714" remote="131691415200000000" Dst="2" />
<file name="page5.html" server="capnum-doc.intranet.dgfip//part/" local="131691405101977214" remote="131691415200000000" Dst="2" />
<file name="page6.html" server="capnum-doc.intranet.dgfip//part/" local="131691405102264714" remote="131691415200000000" Dst="2" />
<file name="page7.html" server="capnum-doc.intranet.dgfip//part/" local="131691405102502214" remote="131691415200000000" Dst="2" />
</dwsync>